sda/__init__.py
sda/element.py
sda/locators.py
sda/mixins.py
sda/page.py
sda/shortcuts.py
sda/site.py
sda/structures.py
sda-1.0.3.dist-info/METADATA
sda-1.0.3.dist-info/RECORD
sda-1.0.3.dist-info/WHEEL
sda-1.0.3.dist-info/top_level.txt
