Metadata-Version: 2.1
Name: sda
Version: 1.0.3
Summary: A wrapper for Selenium. This library uses custom data attributes to accelerate testing through the Selenium framework
Home-page: https://github.com/jlane9/selenium-data-attributes
Author: jlane
Author-email: jlane@fanthreesixty.com
License: MIT
Download-URL: https://github.com/jlane9/selenium-data-attributes/tarball/1.0.3
Keywords: testing selenium qa web automation
Platform: UNKNOWN
Classifier: Development Status :: 5 - Production/Stable
Classifier: Intended Audience :: Developers
Classifier: Programming Language :: Python :: 2.6
Classifier: Programming Language :: Python :: 2.7
Classifier: Programming Language :: Python :: 3.2
Classifier: Programming Language :: Python :: 3.5
Classifier: Programming Language :: Python :: 3.6
Classifier: License :: OSI Approved :: MIT License
Classifier: Topic :: Software Development :: Quality Assurance
Classifier: Topic :: Software Development :: Testing
Requires-Dist: lxml
Requires-Dist: cssselect
